g3elements/__init__.py
g3elements/_elements.py
g3elements/py.typed
g3elements/route_utils/__init__.py
g3elements/route_utils/_analyzer.py
g3elements/route_utils/_manager.py
g3elements/route_utils/_tram.py
g3elements-0.2.1.dist-info/LICENCE
g3elements-0.2.1.dist-info/METADATA
g3elements-0.2.1.dist-info/WHEEL
g3elements-0.2.1.dist-info/top_level.txt
g3elements-0.2.1.dist-info/RECORD
