Metadata-Version: 2.1
Name: g3elements
Version: 0.2.1
Summary: G3 PLC system elements
Author-email: Konstantin Mykhailov <kmykhailov@elektroline.cz>
Project-URL: Homepage, https://gitlab.elektroline.cz/plc/systemg3-py/SystemG3Elements
Keywords: Elektroline,System G3
Classifier: Development Status :: 3 - Alpha
Classifier: Intended Audience :: Developers
Classifier: Intended Audience :: Other Audience
Classifier: License :: OSI Approved :: MIT License
Classifier: Natural Language :: English
Classifier: Operating System :: OS Independent
Classifier: Programming Language :: Python :: 3
Classifier: Programming Language :: Python :: 3 :: Only
Classifier: Programming Language :: Python :: 3.10
Classifier: Programming Language :: Python :: 3.11
Classifier: Programming Language :: Python :: 3.12
Classifier: Topic :: Software Development :: Libraries :: Python Modules
Classifier: Typing :: Typed
Requires-Python: >=3.10
License-File: LICENCE
Requires-Dist: pydantic >=2.0
Requires-Dist: g3tables
